{
    "id": "albot",
    "key": false,
    "name": "ALBot",
    "team": "albot",
    "brain": "// =======================\n// Bot Arena Fight - Updated (3-bot + anti-rush + better evasion)\n// Winner: closest to center with least damage\n// =======================\n\nvar s = context.state, a = context.action, m = context.memory;\nvar PI = Math.PI, PI2 = PI * 2;\n\n// ---------- init ----------\nif (!m.t) { m.t = 0; m.lf = -99; }\nm.t++;\n\nif (m.orbDir === undefined) m.orbDir = (Math.random() < 0.5 ? -1 : 1);\nif (!m.lastRange) m.lastRange = {};        // enemy id -> last range\nif (m.evadeUntil === undefined) m.evadeUntil = 0;\nif (m.lastDamageFrame === undefined) m.lastDamageFrame = -9999;\n\n// ---------- helpers ----------\nvar angDiff = function(x, y) {\n  var d = (x - y) % PI2;\n  if (d > PI) d -= PI2;\n  if (d < -PI) d += PI2;\n  return d;\n};\nvar clamp = function(v, lo, hi){ return Math.max(lo, Math.min(hi, v)); };\n\n// ---------- safe remaining time ----------\nvar rem =\n  (context.round && typeof context.round.remaining === \"number\") ? context.round.remaining :\n  (typeof context.remaining === \"number\") ? context.remaining :\n  30;\n\n// ---------- local state ----------\nvar closest = s.proximity[0] || {};\nvar front   = s.scanner.robot[0] || false;\nvar eProj   = s.scanner.projectile[0] || false;\n\nvar myX = s.position.x, myY = s.position.y, myA = s.angle;\nvar cx = 450, cy = 450;\nvar dxC = myX - cx, dyC = myY - cy;\nvar dC  = Math.sqrt(dxC * dxC + dyC * dyC);\nvar toC = s.angleToCenter;\n\nvar hp = (typeof s.health === \"number\") ? s.health : 100;\nvar lowHP = hp < 35;\n\n// ---------- random micro-jitter (reduced; helps not be perfectly predictable) ----------\nif (Math.random() < 0.002) {\n  a.desiredAngle = s.angle + (Math.random() * (PI/10)) - (PI/20);\n  a.desiredForce = 0;\n}\n\n// ---------- detect nearest enemy + counts ----------\nvar nearbot = false;\nvar nearestEnemy = null, nearestEnemyRange = 1e9;\nvar enemyNearCount = 0;\n\nfor (var j = 0; j < s.proximity.length; j++) {\n  var p = s.proximity[j];\n  if (p.entityType !== \"robot\") continue;\n  if (!p.active) continue;\n  if (p.team === s.team) continue;\n\n  if (p.range < 55 && !nearbot) nearbot = p;\n  if (p.range < 90) enemyNearCount++;\n  if (p.range < nearestEnemyRange) { nearestEnemyRange = p.range; nearestEnemy = p; }\n}\n\n// ---------- ring-control targets (beats last-second rush) ----------\nvar ringTarget =\n  (rem < 9)  ? 55  :\n  (rem < 16) ? 120 :\n              210;\n\nvar ringErr = dC - ringTarget;\n\n// ---------- orbiting default (stable, low-collision) ----------\nvar orbitAngle = toC + m.orbDir * (PI / 2);\na.desiredAngle = orbitAngle;\n\n// base force scales with ring error\nvar base = clamp(Math.abs(ringErr) / 140, 0.15, 1.0);\na.desiredForce = s.maxForce * base;\n\n// radial correction\nif (ringErr > 25) {\n  a.desiredAngle = toC;\n  a.desiredForce = s.maxForce * clamp(ringErr / 220, 0.35, 1.0);\n} else if (ringErr < -25) {\n  a.desiredAngle = (toC + PI) % PI2;\n  a.desiredForce = s.maxForce * clamp((-ringErr) / 220, 0.25, 0.75);\n}\n\n// ---------- wall safety ----------\nif (closest.entityType === \"wall\") {\n  a.desiredAngle = toC + m.orbDir * (PI / 6);\n  a.desiredForce = s.maxForce * 0.9;\n}\n\n// ---------- projectile dodge (ring-aware) ----------\nif (!nearbot && eProj && eProj.range < 110) {\n  var inc = (eProj.angleFromRobot + PI) % PI2;\n  var pD  = Math.abs(angDiff(eProj.angle, inc));\n  if (pD < 0.55) {\n    var pL = eProj.angleFromRobot + PI / 2;\n    var pR = eProj.angleFromRobot - PI / 2;\n\n    var testLx = myX + Math.cos(pL) * 40, testLy = myY + Math.sin(pL) * 40;\n    var testRx = myX + Math.cos(pR) * 40, testRy = myY + Math.sin(pR) * 40;\n    var dCL = Math.sqrt((testLx - cx)*(testLx - cx) + (testLy - cy)*(testLy - cy));\n    var dCR = Math.sqrt((testRx - cx)*(testRx - cx) + (testRy - cy)*(testRy - cy));\n    var errL = Math.abs(dCL - ringTarget);\n    var errR = Math.abs(dCR - ringTarget);\n\n    a.desiredAngle = (errL < errR) ? pL : pR;\n    a.desiredForce = s.maxForce * 0.65;\n  }\n}\n\n// ---------- damage panic (break pins) ----------\nvar justDamaged = false;\nif (s.lastDamage && s.lastDamage.length) {\n  var ld = s.lastDamage[s.lastDamage.length - 1];\n  if (ld.atFrame !== m.lastDamageFrame) {\n    m.lastDamageFrame = ld.atFrame;\n    justDamaged = true;\n  }\n}\nif (justDamaged) {\n  m.evadeUntil = m.t + 14;\n  m.orbDir *= -1;\n}\n\n// ---------- wall risk estimator (for strafing choice) ----------\nvar wallRisk = function(ang) {\n  var nx = myX + Math.cos(ang) * 60;\n  var ny = myY + Math.sin(ang) * 60;\n\n  // Conservative bounds (arena seems ~0..900; sample walls at -5)\n  var left   = Math.max(0, 25 - nx);\n  var right  = Math.max(0, nx - 875);\n  var top    = Math.max(0, 25 - ny);\n  var bottom = Math.max(0, ny - 875);\n  return left*left + right*right + top*top + bottom*bottom;\n};\n\n// ---------- aggressive bot awareness (closing speed) ----------\nvar closing = 0;\nif (nearestEnemy) {\n  var prev = m.lastRange[nearestEnemy.id];\n  if (typeof prev === \"number\") closing = prev - nearestEnemy.range; // >0 => approaching\n  m.lastRange[nearestEnemy.id] = nearestEnemy.range;\n}\n\nvar closeThreat = nearestEnemy && nearestEnemyRange < 65;\nvar chaseThreat = nearestEnemy && nearestEnemyRange < 140 && closing > 0.8;\nvar evade = (m.t < m.evadeUntil) || closeThreat || chaseThreat;\n\n// ---------- evasion: strafe + wall-aware ----------\nif (evade && nearestEnemy) {\n  var leftStrafe  = nearestEnemy.angleFromRobot + PI / 2;\n  var rightStrafe = nearestEnemy.angleFromRobot - PI / 2;\n\n  var riskL = wallRisk(leftStrafe);\n  var riskR = wallRisk(rightStrafe);\n  var strafe = (riskL < riskR) ? leftStrafe : rightStrafe;\n\n  var away = (nearestEnemy.angleFromRobot + PI) % PI2;\n\n  // very close: bias to away/quick-turn so we don't eat a ram\n  if (nearestEnemyRange < 45) {\n    strafe = (Math.abs(angDiff(myA, strafe)) < Math.abs(angDiff(myA, away))) ? strafe : away;\n  }\n\n  var wallIsClosest = (closest && closest.entityType === \"wall\" && closest.range < 55);\n  var f = s.maxForce * (nearestEnemyRange < 70 ? 1.0 : 0.85);\n  if (wallIsClosest) f = s.maxForce * 0.75;\n\n  a.desiredAngle = strafe;\n  a.desiredForce = f;\n\n  // deterrent shot if lined up and not in immediate ram range\n  if (front && front.active && front.team != s.team && nearestEnemyRange < 140 && (m.t - m.lf) >= 28) {\n    var aeDet = Math.abs(angDiff(myA, front.angleFromRobot));\n    if (aeDet < 0.22) { a.desiredLaunch = true; m.lf = m.t; }\n  }\n}\n\n// ---------- disengage logic (avoid \"fight to death\" in 3-bot chaos) ----------\nvar risky = lowHP || (enemyNearCount >= 2 && rem > 6);\nif (nearestEnemy && risky && !evade) {\n  var away2 = (nearestEnemy.angleFromRobot + PI) % PI2;\n  a.desiredAngle = away2 + m.orbDir * (PI / 6);\n  a.desiredForce = s.maxForce * 0.85;\n}\n\n// ---------- shooting with lead + anti-rush punish ----------\nif (front && front.active && front.team != s.team) {\n  var r = front.range;\n\n  // lead\n  var ps = 42;\n  var tF = r / ps;\n  var lx = front.x + front.speed * Math.cos(front.angle) * tF;\n  var ly = front.y + front.speed * Math.sin(front.angle) * tF;\n  var lA = Math.atan2(ly - myY, lx - myX);\n\n  // aim only if not heavily evading / not risky\n  if (!evade && !risky && !nearbot) a.desiredAngle = lA;\n\n  // detect \"rusher toward center\" late game\n  var ex = front.x - cx, ey = front.y - cy;\n  var enemyDC = Math.sqrt(ex*ex + ey*ey);\n  var enemyToC = Math.atan2(cy - front.y, cx - front.x);\n  var enemyHeadingToCenter = Math.abs(angDiff(front.angle, enemyToC)) < 0.55;\n\n  var late = rem < 9;\n  var punishRusher = late && enemyHeadingToCenter && enemyDC > 35;\n\n  var ae = Math.abs(angDiff(myA, lA));\n  var tol = Math.atan2(28, r) + (punishRusher ? 0.12 : 0.0);\n\n  if (!nearbot && (m.t - m.lf) >= 28) {\n    if (!lowHP || punishRusher) {\n      if (ae < tol) {\n        a.desiredLaunch = true;\n        m.lf = m.t;\n      }\n    }\n  }\n}\n\n// ---------- close-quarters collision avoidance (sidestep, don't reverse) ----------\nif (nearbot && rem >= 3.5) {\n  a.desiredAngle = (nearbot.angleFromRobot + m.orbDir * (PI / 2)) % PI2;\n  a.desiredForce = s.maxForce * 0.7;\n}\n\n// ---------- endgame: take/hold center (but avoid last-second ram) ----------\nif (rem < 3.5) {\n  if (dC > 10) {\n    a.desiredAngle = toC;\n    a.desiredForce = s.maxForce;\n  } else {\n    a.desiredForce = 0;\n  }\n\n  if (nearestEnemy && nearestEnemyRange < 70) {\n    a.desiredAngle = toC + m.orbDir * (PI / 2);\n    a.desiredForce = s.maxForce * 0.55;\n  }\n}",
    "version": 1,
    "updated": "2026-03-03T09:25:50.356Z",
    "oldBrains": []
}